genice_diffr/__init__.py
genice_diffr/formats/_Diffr.py
genice_diffr/formats/__init__.py
genice_diffr-0.1.1.dist-info/DESCRIPTION.rst
genice_diffr-0.1.1.dist-info/METADATA
genice_diffr-0.1.1.dist-info/RECORD
genice_diffr-0.1.1.dist-info/WHEEL
genice_diffr-0.1.1.dist-info/entry_points.txt
genice_diffr-0.1.1.dist-info/metadata.json
genice_diffr-0.1.1.dist-info/top_level.txt
