Metadata-Version: 2.0
Name: genice-diffr
Version: 0.1.1
Summary: Diffraction plugin for GenIce.
Home-page: https://github.com/vitroid/genice-diffr/
Author: Masakazu Matsumoto
Author-email: vitroid@gmail.com
License: MIT
Keywords: genice,diffraction,yaplot
Platform: UNKNOWN
Classifier: Development Status :: 4 - Beta
Classifier: Intended Audience :: Developers
Classifier: Programming Language :: Python
Classifier: Programming Language :: Python :: 3.5
Requires-Dist: GenIce (>=0.23)
Requires-Dist: contour3d
Requires-Dist: yaplotlib
